pyBusylight-0.9.2.dist-info/DESCRIPTION.rst
pyBusylight-0.9.2.dist-info/METADATA
pyBusylight-0.9.2.dist-info/RECORD
pyBusylight-0.9.2.dist-info/WHEEL
pyBusylight-0.9.2.dist-info/metadata.json
pyBusylight-0.9.2.dist-info/top_level.txt
pybusylight/__init__.py
pybusylight/color_constants.py
pybusylight/pybusylight.py
