Metadata-Version: 2.0
Name: pyBusylight
Version: 0.9.2
Summary: Python Library for Kuando Busylight device.
Home-page: https://github.com/ericpulvino/pyBusylight
Author: Eric Pulvino
Author-email: ericpulvino@gmail.com
License: MIT
Project-URL: Documentation, https://github.com/ericpulvino/pyBusylight/docs
Project-URL: Source, https://github.com/ericpulvino/pyBusylight
Project-URL: Tracker, https://github.com/ericpulvino/pyBusylight/issues
Keywords: kuando busylight
Platform: UNKNOWN
Classifier: Development Status :: 4 - Beta
Classifier: Intended Audience :: Developers
Classifier: Topic :: System :: Hardware :: Hardware Drivers
Classifier: License :: OSI Approved :: MIT License
Classifier: Programming Language :: Python :: 2
Classifier: Programming Language :: Python :: 2.7
Classifier: Programming Language :: Python :: 3
Classifier: Programming Language :: Python :: 3.6
Requires-Python: >=2.7
Requires-Dist: setuptools
Requires-Dist: pyusb
